{"https://www3.animeflv.net":{"{9743a9bb-854f-4c60-9839-2a861e227208}":{"id":"{9743a9bb-854f-4c60-9839-2a861e227208}","title":"","dir":"auto","lang":"","body":"","tag":"","icon":"","alertName":"https://www3.animeflv.net#notag:{9743a9bb-854f-4c60-9839-2a861e227208}","timestamp":1672667245878,"origin":"https://www3.animeflv.net","data":"","mozbehavior":"{\"noclear\":false,\"noscreen\":false,\"showOnlyOnce\":false,\"soundFile\":\"\"}","serviceWorkerRegistrationScope":""},"{4b6b55e8-a7ef-4ae2-bfaf-8b9312f12250}":{"id":"{4b6b55e8-a7ef-4ae2-bfaf-8b9312f12250}","title":"","dir":"auto","lang":"","body":"","tag":"","icon":"","alertName":"https://www3.animeflv.net#notag:{4b6b55e8-a7ef-4ae2-bfaf-8b9312f12250}","timestamp":1672667250190,"origin":"https://www3.animeflv.net","data":"","mozbehavior":"{\"noclear\":false,\"noscreen\":false,\"showOnlyOnce\":false,\"soundFile\":\"\"}","serviceWorkerRegistrationScope":""},"{ce01529c-7b2b-4f9c-a701-c8ff1407aea0}":{"id":"{ce01529c-7b2b-4f9c-a701-c8ff1407aea0}","title":"","dir":"auto","lang":"","body":"","tag":"","icon":"","alertName":"https://www3.animeflv.net#notag:{ce01529c-7b2b-4f9c-a701-c8ff1407aea0}","timestamp":1672667250657,"origin":"https://www3.animeflv.net","data":"","mozbehavior":"{\"noclear\":false,\"noscreen\":false,\"showOnlyOnce\":false,\"soundFile\":\"\"}","serviceWorkerRegistrationScope":""}}}